{
  "products": [
    {
      "id": "d845531a-2d96-4542-b0fe-142d83dfaf0d",
      "title": "Product One",
      "description": "Desc One",
      "price": "100"
    },
    {
      "id": "b9963a83-c3f8-46cc-b34f-d2532f68147d",
      "title": "Product Two",
      "description": "Desc Two",
      "price": "200"
    },
    {
      "id": "65e29b3c-83cd-4370-b69a-bd5a89801ccb",
      "title": "Product Three",
      "description": "third desc",
      "price": "450"
    },
    {
      "id": "814994dc-ff84-45a8-94f2-9e81a6cdf844",
      "title": "Product four",
      "description": "desc four",
      "price": "20"
    }
  ]
}